artexhibitionlib/__init__.py
artexhibitionlib/enquiry_response.py
artexhibitionlib-0.2.0.dist-info/LICENSE
artexhibitionlib-0.2.0.dist-info/METADATA
artexhibitionlib-0.2.0.dist-info/WHEEL
artexhibitionlib-0.2.0.dist-info/top_level.txt
artexhibitionlib-0.2.0.dist-info/RECORD
